django_generic_flatblocks/__init__.py
django_generic_flatblocks/admin.py
django_generic_flatblocks/models.py
django_generic_flatblocks/contrib/__init__.py
django_generic_flatblocks/contrib/gblocks/__init__.py
django_generic_flatblocks/contrib/gblocks/admin.py
django_generic_flatblocks/contrib/gblocks/models.py
django_generic_flatblocks/contrib/gblocks/migrations/0001_initial.py
django_generic_flatblocks/contrib/gblocks/migrations/__init__.py
django_generic_flatblocks/contrib/gblocks/templates/gblocks/image/flatblock.html
django_generic_flatblocks/contrib/gblocks/templates/gblocks/text/flatblock.html
django_generic_flatblocks/contrib/gblocks/templates/gblocks/title/flatblock.html
django_generic_flatblocks/contrib/gblocks/templates/gblocks/titleandtext/flatblock.html
django_generic_flatblocks/contrib/gblocks/templates/gblocks/titletextandimage/flatblock.html
django_generic_flatblocks/locale/de/LC_MESSAGES/django.po
django_generic_flatblocks/locale/dk/LC_MESSAGES/django.po
django_generic_flatblocks/locale/en/LC_MESSAGES/django.po
django_generic_flatblocks/locale/fr/LC_MESSAGES/django.po
django_generic_flatblocks/migrations/0001_initial.py
django_generic_flatblocks/migrations/__init__.py
django_generic_flatblocks/templates/admin/django_generic_flatblocks/change_form_forward.html
django_generic_flatblocks/templatetags/__init__.py
django_generic_flatblocks/templatetags/generic_flatblocks.py
django_generic_flatblocks/tests/__init__.py
django_generic_flatblocks/tests/test_flatblocks.py
django_generic_flatblocks/tests/templates/test_template.html
django_generic_flatblocks/tests/templates/auth/user/flatblock.html
django_generic_flatblocks/tests/templates/auth/user/flatblock_firstname.html
django_generic_flatblocks/tests/testapp/__init__.py
django_generic_flatblocks/tests/testapp/settings.py
django_generic_flatblocks/tests/testapp/urls.py
django_generic_flatblocks-1.3.dist-info/METADATA
django_generic_flatblocks-1.3.dist-info/RECORD
django_generic_flatblocks-1.3.dist-info/WHEEL
django_generic_flatblocks-1.3.dist-info/top_level.txt
