Metadata-Version: 2.1
Name: django-generic-flatblocks
Version: 1.3
Summary: 
Requires-Dist: django (>=1.8)
Requires-Dist: pillow
